LICENSE.txt
MANIFEST.in
README.md
requirements.txt
setup.cfg
setup.py
monitoring_template/__init__.py
monitoring_template/core.py
monitoring_template.egg-info/PKG-INFO
monitoring_template.egg-info/SOURCES.txt
monitoring_template.egg-info/dependency_links.txt
monitoring_template.egg-info/entry_points.txt
monitoring_template.egg-info/not-zip-safe
monitoring_template.egg-info/requires.txt
monitoring_template.egg-info/top_level.txt
monitoring_template/api/__init__.py
monitoring_template/api/namespaces/__init__.py
monitoring_template/settings/__init__.py
monitoring_template/settings/global_settings.py
monitoring_template/tools/__init__.py
monitoring_template/tools/logger.py
monitoring_template/tools/prometheus_metrics.py
monitoring_template/tools/tracer.py