Metadata-Version: 1.0
Name: monitoring-template
Version: 0.0.2
Summary: Monitoring template
Home-page: UNKNOWN
Author: UNKNOWN
Author-email: UNKNOWN
License: UNKNOWN
Platform: UNKNOWN
